<annotation>
	<folder>Data</folder>
	<filename>images (58).jpg</filename>
	<path>C:\Users\dhruva.gupta\Documents\Projects\Object Detection\Guitars\Data\images (58).jpg</path>
	<source>
		<database>Unknown</database>
	</source>
	<size>
		<width>295</width>
		<height>171</height>
		<depth>3</depth>
	</size>
	<segmented>0</segmented>
	<object>
		<name>acoustic</name>
		<pose>Unspecified</pose>
		<truncated>0</truncated>
		<difficult>0</difficult>
		<bndbox>
			<xmin>6</xmin>
			<ymin>20</ymin>
			<xmax>291</xmax>
			<ymax>148</ymax>
		</bndbox>
	</object>
</annotation>
